my_own_package/__init__.py
ana_tanase_own_package-0.2.0.dist-info/METADATA
ana_tanase_own_package-0.2.0.dist-info/WHEEL
ana_tanase_own_package-0.2.0.dist-info/top_level.txt
ana_tanase_own_package-0.2.0.dist-info/RECORD
