Metadata-Version: 2.1
Name: ana-tanase-own-package
Version: 0.2.0
Summary: my_first_package
Author: Ana Tanase
Author-email: tanase_ana253@yahoo.com
